asyncio-precedence.pth
contextvars.py
asyncio/__init__.py
asyncio/_asyncio.cp36-win_amd64.pyd
asyncio/_version.py
asyncio/base_events.py
asyncio/base_futures.py
asyncio/base_subprocess.py
asyncio/base_tasks.py
asyncio/constants.py
asyncio/coroutines.py
asyncio/events.py
asyncio/format_helpers.py
asyncio/futures.py
asyncio/locks.py
asyncio/log.py
asyncio/proactor_events.py
asyncio/protocols.py
asyncio/queues.py
asyncio/runners.py
asyncio/selector_events.py
asyncio/sslproto.py
asyncio/streams.py
asyncio/subprocess.py
asyncio/tasks.py
asyncio/transports.py
asyncio/unix_events.py
asyncio/windows_events.py
asyncio/windows_utils.py
asyncio37-0.1.3.dist-info/LICENSE
asyncio37-0.1.3.dist-info/METADATA
asyncio37-0.1.3.dist-info/WHEEL
asyncio37-0.1.3.dist-info/top_level.txt
asyncio37-0.1.3.dist-info/RECORD
