Metadata-Version: 2.1
Name: asyncio37
Version: 0.1.3
Summary: Backport of asyncio in Python 3.7
Home-page: https://github.com/mars-project/asyncio37
Author: Wenjun Si
Author-email: swj0066@gmail.com
License: UNKNOWN
Platform: UNKNOWN
Classifier: Operating System :: OS Independent
Classifier: Programming Language :: Python
Classifier: Programming Language :: Python :: 3.6
Classifier: Programming Language :: Python :: Implementation :: CPython
Classifier: Topic :: Software Development :: Libraries
